{
"texture":"../images/p2_xin.png",
"tangentialAcceleration":0
,"maxRadiusVariance":30
,"lifespan":2230
,"tangentialAccelerationVariance":0
,"minRadius":20
,"lifespanVariance":700
,"startBlueVariance":0
,"minRadiusVariance":10
,"startSize":50
,"startGreenVariance":0
,"rotatePerSecond":30
,"startSizeVariance":10
,"startGreen":255
,"rotatePerSecondVariance":10
,"endSize":30
,"startAlphaVariance":0
,"emitterType":0
,"emitAngle":180
,"startBlue":255
,"emitAngleVariance":30
,"endRed":255
,"startAlpha":0.618
,"startRotation":0
,"startRotationVariance":45
,"endBlue":255
,"endRotation":45
,"endAlpha":1
,"endSizeVariance":5
,"endRotationVariance":292.07
,"maxRadius":100
,"startRed":255
,"endAlphaVariance":0
,"endGreen":255
,"gravity":{"x":0,"y":-110}
,"speedVariance":0
,"maxParticles":5
,"endBlueVariance":0
,"endRedVariance":0
,"speed":20
,"radialAcceleration":0
,"startRedVariance":0
,"radialAccelerationVariance":0
,"duration":-1
,"blendFactorSource":"one"
,"blendFactorDestination":"oneMinusSourceAlpha"
,"emitterVariance":{"x":100,"y":38}
,"emitter":{"x":0,"y":0}
,"engGreenVariance":0
}